convrewriting/__init__.py
convrewriting/data/bert_models/pred_BERT_MSMARCO_step1.tsv
convrewriting/data/bert_models/pred_BERT_MSMARCO_step2.tsv
convrewriting/data/datasets/test_df.pkl
convrewriting/data/datasets/test_set.tsv
convrewriting/data/datasets/train_df.pkl
convrewriting/data/datasets/training_set.tsv
convrewriting/data/gbdt_features/test_features_step1.pkl
convrewriting/data/gbdt_features/test_features_step2_all_feat_lightGBM_S1_BERT.pkl
convrewriting/supervised/__init__.py
convrewriting/supervised/pipeline_classification.py
convrewriting/supervised/topic_utils.py
convrewriting/unsupervised/__init__.py
convrewriting/unsupervised/pipeline_nlp.py
convrewriting/unsupervised/source.py
convrewriting/unsupervised/topic.py
convrewriting-0.0.1.dist-info/LICENSE
convrewriting-0.0.1.dist-info/METADATA
convrewriting-0.0.1.dist-info/WHEEL
convrewriting-0.0.1.dist-info/top_level.txt
convrewriting-0.0.1.dist-info/RECORD
