Metadata-Version: 2.1
Name: convrewriting
Version: 0.0.1
Summary: Question rewriting for conversational search based on unsupervised and supervised methods.
Home-page: https://github.com/hpclab/adaptive-utterance-rewriting-conversational-search
Author: Cristina Muntean
Author-email: cristina.muntean@isti.cnr.it
Classifier: Programming Language :: Python :: 3
Classifier: Programming Language :: Python :: 3.7
Classifier: License :: OSI Approved :: MIT License
Classifier: Operating System :: OS Independent
Requires-Python: >=3.7
License-File: LICENSE
